AUTHORS.rst
LICENSE
MANIFEST.in
README.md
requirements.txt
setup.py
virtualenv_mgr.egg-info/PKG-INFO
virtualenv_mgr.egg-info/SOURCES.txt
virtualenv_mgr.egg-info/dependency_links.txt
virtualenv_mgr.egg-info/not-zip-safe
virtualenv_mgr.egg-info/requires.txt
virtualenv_mgr.egg-info/top_level.txt
virtualenvmgr/__init__.py
virtualenvmgr/envmanager.py
virtualenvmgr/piphisto.py
virtualenvmgr/utils.py
virtualenvmgr/virtualenv-mgr