Metadata-Version: 1.0
Name: virtualenv-mgr
Version: 1.0.3
Summary: Tool to manage your virtualenvs
Home-page: https://github.com/arteria/virtualenv-mgr
Author: arteria
Author-email: admin@arteria.ch
License: BSD
Platform: UNKNOWN
